SVGVideoMaker/__init__.py
SVGVideoMaker/parser.py
SVGVideoMaker/video.py
SVGVideoMaker/Documentation/__init__.py
SVGVideoMaker/Documentation/conf.py
SVGVideoMaker/examples/Colors.py
SVGVideoMaker/examples/EllipseArc.py
SVGVideoMaker/examples/Parser.py
SVGVideoMaker/examples/Polygon.py
SVGVideoMaker/examples/__init__.py
SVGVideoMaker/geo/__init__.py
SVGVideoMaker/geo/animation.py
SVGVideoMaker/geo/arc.py
SVGVideoMaker/geo/debug.py
SVGVideoMaker/geo/ellipse.py
SVGVideoMaker/geo/gradient.py
SVGVideoMaker/geo/group.py
SVGVideoMaker/geo/point.py
SVGVideoMaker/geo/polygon.py
SVGVideoMaker/geo/quadrant.py
SVGVideoMaker/geo/rectangle.py
SVGVideoMaker/geo/segment.py
SVGVideoMaker/geo/shape.py
SVGVideoMaker/geo/style.py
SVGVideoMaker/geo/svg.py
SVGVideoMaker/geo/utility.py
SVGVideoMaker-0.4.3.dist-info/METADATA
SVGVideoMaker-0.4.3.dist-info/WHEEL
SVGVideoMaker-0.4.3.dist-info/top_level.txt
SVGVideoMaker-0.4.3.dist-info/RECORD
