Metadata-Version: 2.1
Name: SVGVideoMaker
Version: 0.4.3
Summary: Creator of video from svg with cairosvg, ffmpeg
Home-page: https://github.com/evayann/SVGVideoMaker
Author: Yann Zavattero
Author-email: yann.zavattero@hotmail.com
License: UNKNOWN
Platform: UNKNOWN
Classifier: Programming Language :: Python :: 3
Classifier: License :: OSI Approved :: MIT License
Classifier: Operating System :: OS Independent
Requires-Python: >=3.6
